[
    {
        "name": "rawlocation_id",
        "type": "STRING",
        "mode": "NULLABLE",
        "description": "unique id"
    },
    {
        "name": "location_id",
        "type": "STRING",
        "mode": "NULLABLE",
        "description": "unique location id generated by the disambiguation algorithm"
    },
    {
        "name": "raw_city",
        "type": "STRING",
        "mode": "NULLABLE",
        "description": "city associated with a location_id"
    },
    {
        "name": "raw_state",
        "type": "STRING",
        "mode": "NULLABLE",
        "description": "state associated with a location_id"
    },
    {
        "name": "raw_country",
        "type": "INTEGER",
        "mode": "NULLABLE",
        "description": "country associated with a location_id"
    }
]